zonar_ds_logger/__init__.py
zonar_ds_logger/logger.py
zonar_ds_logger-1.0.0.dist-info/LICENSE
zonar_ds_logger-1.0.0.dist-info/METADATA
zonar_ds_logger-1.0.0.dist-info/WHEEL
zonar_ds_logger-1.0.0.dist-info/top_level.txt
zonar_ds_logger-1.0.0.dist-info/RECORD
