Metadata-Version: 2.1
Name: zonar-ds-logger
Version: 1.0.0
Summary: Python logger helper to log in json and redirect flask logs
Home-page: https://github.com/evcallia/zonar_ds_logger.git
Author: Zonar Systems - Data Services Pod
Author-email: dspod@zonarsystems.com
License: UNKNOWN
Platform: UNKNOWN
Classifier: Programming Language :: Python :: 3
Classifier: License :: OSI Approved :: MIT License
Classifier: Operating System :: OS Independent
Requires-Dist: python-json-logger (==0.1.11)
